{"data":{"Year":["2014","2019","2019","2019","2019","2019","2019","2019","2019"],"OBS_STATUS":["A","A","A","A","A","A","A","A","A"],"UNIT_MULT":["0","0","0","0","0","0","0","0","0"],"NATURE":["_X","_X","_X","_X","_X","_X","_X","_X","_X"],"SOURCE_DETAIL":["Nepal Multiple Indicator Cluster Survey 2014 and 2019","Nepal Multiple Indicator Cluster Survey 2014 and 2019","Nepal Multiple Indicator Cluster Survey 2014 and 2019","Nepal Multiple Indicator Cluster Survey 2014 and 2019","Nepal Multiple Indicator Cluster Survey 2014 and 2019","Nepal Multiple Indicator Cluster Survey 2014 and 2019","Nepal Multiple Indicator Cluster Survey 2014 and 2019","Nepal Multiple Indicator Cluster Survey 2014 and 2019","Nepal Multiple Indicator Cluster Survey 2014 and 2019"],"FREQ":["A","A","A","A","A","A","A","A","A"],"REPORTING_TYPE":["N","N","N","N","N","N","N","N","N"],"SERIES":["SE_DEV_ONTRK","SE_DEV_ONTRK","SE_DEV_ONTRK","SE_DEV_ONTRK","SE_DEV_ONTRK","SE_DEV_ONTRK","SE_DEV_ONTRK","SE_DEV_ONTRK","SE_DEV_ONTRK"],"REF_AREA":[null,null,"NP1","NP2","NP3","NP4","NP5","NP6","NP7"],"UNIT_MEASURE":["PT","PT","PT","PT","PT","PT","PT","PT","PT"],"Value":[64.4,65.2,76.9,55.8,73.9,79.5,60.0,55.0,59.9]},"edges":{"From":["OBS_STATUS","UNIT_MULT","NATURE","SOURCE_DETAIL","FREQ","REPORTING_TYPE"],"To":["UNIT_MULT","NATURE","SOURCE_DETAIL","FREQ","REPORTING_TYPE","REF_AREA"]}}